EAS2Text/EAS2Text.py
EAS2Text/__init__.py
EAS2Text-0.1.12.dist-info/LICENSE
EAS2Text-0.1.12.dist-info/METADATA
EAS2Text-0.1.12.dist-info/WHEEL
EAS2Text-0.1.12.dist-info/top_level.txt
EAS2Text-0.1.12.dist-info/RECORD
